[
    {
      "image": "../Images/VacationIdeas/phuket.jpg",
      "heading": "Phuket's Best Pool Villas"
    },
    {
      "image": "../Images/VacationIdeas/coorg.jpg",
      "heading": "Coorg Homestays"
    },
    {
      "image": "../Images/VacationIdeas/family.jpg",
      "heading": "Family Bungalows in Lonavala"
    },
    {
      "image": "../Images/VacationIdeas/bali.jpg",
      "heading": "Bali Family Villas"
    },
    {
      "image": "../Images/VacationIdeas/sri_lanka.jpg",
      "heading": "Sri Lanka - Rural solitude and luxury combined"
    },
    {
      "image": "../Images/VacationIdeas/apartments.jpg",
      "heading": "Apartments near the Louvre in Paris"
    },
    {
      "image": "../Images/VacationIdeas/cheap.png",
      "heading": "Cheap & Affordable Homestays & Resorts in Sakleshpur"
    },
    {
      "image": "../Images/VacationIdeas/luxury.jpg",
      "heading": "Luxury Vacation in Goa"
    },
    {
      "image": "../Images/VacationIdeas/top.jpeg",
      "heading": "Top Homestays and resorts in Chikmagalur"
    },
    {
      "image": "../Images/VacationIdeas/nilgris.jpg",
      "heading": "Escape to the Nilgiris - Homestays, Resorts, Cottages in Coonoor"
    }
]